thyra/__init__.py
thyra/__main__.py
thyra/alignment/__init__.py
thyra/alignment/affine.py
thyra/alignment/teaching_points.py
thyra/config.py
thyra/convert.py
thyra/converters/__init__.py
thyra/converters/spatialdata/__init__.py
thyra/converters/spatialdata/base_spatialdata_converter.py
thyra/converters/spatialdata/converter.py
thyra/converters/spatialdata/spatialdata_2d_converter.py
thyra/converters/spatialdata/spatialdata_3d_converter.py
thyra/converters/spatialdata/streaming_converter.py
thyra/core/__init__.py
thyra/core/base_converter.py
thyra/core/base_extractor.py
thyra/core/base_reader.py
thyra/core/registry.py
thyra/metadata/__init__.py
thyra/metadata/extractors/__init__.py
thyra/metadata/extractors/bruker_extractor.py
thyra/metadata/extractors/imzml_extractor.py
thyra/metadata/ontology/__init__.py
thyra/metadata/ontology/_ims.py
thyra/metadata/ontology/_ms.py
thyra/metadata/ontology/_uo.py
thyra/metadata/ontology/cache.py
thyra/metadata/types.py
thyra/metadata/validator.py
thyra/readers/__init__.py
thyra/readers/bruker/__init__.py
thyra/readers/bruker/base_bruker_reader.py
thyra/readers/bruker/folder_structure.py
thyra/readers/bruker/rapiflex/__init__.py
thyra/readers/bruker/rapiflex/rapiflex_reader.py
thyra/readers/bruker/timstof/__init__.py
thyra/readers/bruker/timstof/sdk/__init__.py
thyra/readers/bruker/timstof/sdk/dll/README.md
thyra/readers/bruker/timstof/sdk/dll/timsdata.dll
thyra/readers/bruker/timstof/sdk/dll/timsdata.so
thyra/readers/bruker/timstof/sdk/dll_manager.py
thyra/readers/bruker/timstof/sdk/platform_detector.py
thyra/readers/bruker/timstof/sdk/sdk_functions.py
thyra/readers/bruker/timstof/timstof_reader.py
thyra/readers/bruker/timstof/utils/__init__.py
thyra/readers/bruker/timstof/utils/batch_processor.py
thyra/readers/bruker/timstof/utils/coordinate_cache.py
thyra/readers/bruker/timstof/utils/mass_axis_builder.py
thyra/readers/bruker/timstof/utils/memory_manager.py
thyra/readers/imzml/__init__.py
thyra/readers/imzml/imzml_reader.py
thyra-1.13.0.dist-info/METADATA
thyra-1.13.0.dist-info/WHEEL
thyra-1.13.0.dist-info/entry_points.txt
thyra-1.13.0.dist-info/licenses/LICENSE
thyra-1.13.0.dist-info/RECORD
