Metadata-Version: 2.4
Name: thyra
Version: 1.13.0
Summary: A modern Python library for converting Mass Spectrometry Imaging (MSI) data into SpatialData/Zarr format - your portal to spatial omics
License: MIT
License-File: LICENSE
Keywords: mass-spectrometry,imaging,spatialdata,zarr,omics,bioinformatics,msi,imzml,bruker,spatial-omics,data-conversion,scientific-computing
Author: Theodoros Visvikis
Author-email: t.visvikis@maastrichtuniversity.nl
Maintainer: Theodoros Visvikis
Maintainer-email: t.visvikis@maastrichtuniversity.nl
Requires-Python: >=3.11,<3.13
Classifier: Development Status :: 4 - Beta
Classifier: Environment :: Console
Classifier: Intended Audience :: Science/Research
Classifier: License :: OSI Approved :: MIT License
Classifier: Operating System :: OS Independent
Classifier: Programming Language :: Python :: 3
Classifier: Programming Language :: Python :: 3.11
Classifier: Programming Language :: Python :: 3.12
Classifier: Programming Language :: Python :: 3.10
Classifier: Topic :: File Formats
Classifier: Topic :: Scientific/Engineering :: Bio-Informatics
Classifier: Topic :: Scientific/Engineering :: Information Analysis
Classifier: Topic :: Scientific/Engineering :: Medical Science Apps.
Classifier: Topic :: Software Development :: Libraries :: Python Modules
Classifier: Typing :: Typed
Requires-Dist: Shapely (>=1.8.0)
Requires-Dist: anndata (>=0.11.0)
Requires-Dist: cryptography (>=45.0.5,<46.0.0)
Requires-Dist: dask (>=2023.0.0)
Requires-Dist: geopandas (>=0.9.0)
Requires-Dist: imagecodecs (>=2024.1.1)
Requires-Dist: lxml (>=4.6.0)
Requires-Dist: matplotlib (>=3.10.6,<4.0.0)
Requires-Dist: numpy (>=2.0.0)
Requires-Dist: pandas (>=2.0.0)
Requires-Dist: psutil (>=7.2.1,<8.0.0)
Requires-Dist: pyimzML (>=1.4.0)
Requires-Dist: scipy (>=1.7.0)
Requires-Dist: spatialdata (>=0.6.0)
Requires-Dist: tqdm (>=4.50.0)
Requires-Dist: zarr (>=3.0.0)
Project-URL: Bug Tracker, https://github.com/Tomatokeftes/thyra/issues
Project-URL: Changelog, https://github.com/Tomatokeftes/thyra/blob/main/CHANGELOG.md
Project-URL: Contributing, https://github.com/Tomatokeftes/thyra/blob/main/CONTRIBUTING.md
Project-URL: Documentation, https://github.com/Tomatokeftes/thyra#readme
Project-URL: Discussions, https://github.com/Tomatokeftes/thyra/discussions
Project-URL: Homepage, https://github.com/Tomatokeftes/thyra
Project-URL: Repository, https://github.com/Tomatokeftes/thyra
